TesterhomeWikiAppiumGaojiJinjieJiaochengFix1/README.md
TesterhomeWikiAppiumGaojiJinjieJiaochengFix1/__init__.py
TesterhomeWikiAppiumGaojiJinjieJiaochengFix1/__main__.py
TesterhomeWikiAppiumGaojiJinjieJiaochengFix1/file.epub
TesterhomeWikiAppiumGaojiJinjieJiaochengFix1/index.html
TesterhomeWikiAppiumGaojiJinjieJiaochengFix1/css/__init__.py
TesterhomeWikiAppiumGaojiJinjieJiaochengFix1/css/annotations.css
TesterhomeWikiAppiumGaojiJinjieJiaochengFix1/css/main.css
TesterhomeWikiAppiumGaojiJinjieJiaochengFix1/css/normalize.css
TesterhomeWikiAppiumGaojiJinjieJiaochengFix1/css/popup.css
TesterhomeWikiAppiumGaojiJinjieJiaochengFix1/font/__init__.py
TesterhomeWikiAppiumGaojiJinjieJiaochengFix1/font/fontello.eot
TesterhomeWikiAppiumGaojiJinjieJiaochengFix1/font/fontello.svg
TesterhomeWikiAppiumGaojiJinjieJiaochengFix1/font/fontello.ttf
TesterhomeWikiAppiumGaojiJinjieJiaochengFix1/font/fontello.woff
TesterhomeWikiAppiumGaojiJinjieJiaochengFix1/img/__init__.py
TesterhomeWikiAppiumGaojiJinjieJiaochengFix1/img/annotator-glyph-sprite.png
TesterhomeWikiAppiumGaojiJinjieJiaochengFix1/img/annotator-icon-sprite.png
TesterhomeWikiAppiumGaojiJinjieJiaochengFix1/img/apple-touch-icon.png
TesterhomeWikiAppiumGaojiJinjieJiaochengFix1/img/cancelfullscreen.png
TesterhomeWikiAppiumGaojiJinjieJiaochengFix1/img/close.png
TesterhomeWikiAppiumGaojiJinjieJiaochengFix1/img/fullscreen.png
TesterhomeWikiAppiumGaojiJinjieJiaochengFix1/img/loader.gif
TesterhomeWikiAppiumGaojiJinjieJiaochengFix1/img/menu-icon.png
TesterhomeWikiAppiumGaojiJinjieJiaochengFix1/img/save.png
TesterhomeWikiAppiumGaojiJinjieJiaochengFix1/img/saved.png
TesterhomeWikiAppiumGaojiJinjieJiaochengFix1/img/settings-s.png
TesterhomeWikiAppiumGaojiJinjieJiaochengFix1/img/settings.png
TesterhomeWikiAppiumGaojiJinjieJiaochengFix1/img/star.png
TesterhomeWikiAppiumGaojiJinjieJiaochengFix1/js/__init__.py
TesterhomeWikiAppiumGaojiJinjieJiaochengFix1/js/epub.js
TesterhomeWikiAppiumGaojiJinjieJiaochengFix1/js/epub.min.js
testerhome_wiki_appium_gaoji_jinjie_jiaocheng_fix1-2025.3.25.1.dist-info/METADATA
testerhome_wiki_appium_gaoji_jinjie_jiaocheng_fix1-2025.3.25.1.dist-info/WHEEL
testerhome_wiki_appium_gaoji_jinjie_jiaocheng_fix1-2025.3.25.1.dist-info/entry_points.txt
testerhome_wiki_appium_gaoji_jinjie_jiaocheng_fix1-2025.3.25.1.dist-info/top_level.txt
testerhome_wiki_appium_gaoji_jinjie_jiaocheng_fix1-2025.3.25.1.dist-info/RECORD
